{"meta":{"learningDate":[2023,10,13,15,26],"applyDate":[2023,10,13,15,26],"method":"Relation","algorithm":["CosineSimilarity"]},"nodes":[{"id":"6","name":"잠실6동","type":"FILE","user":"SY"},{"id":"72","name":"성내2동","type":"FILE","user":"JH"},{"id":"73","name":"문정2동","type":"FILE","user":"Gasfard"},{"id":"126","name":"장지동","type":"FILE","user":"Santiago"},{"id":"142","name":"석촌동","type":"FILE","user":"JY"},{"id":"143","name":"위례동","type":"FILE","user":"Royd"},{"id":"160","name":"오금동","type":"FILE","user":"Pierre"},{"id":"190","name":"송파1동","type":"FILE","user":"Pel"},{"id":"202","name":"길동","type":"FILE","user":"JH"},{"id":"219","name":"마천2동","type":"FILE","user":"Pierre"},{"id":"237","name":"마천1동","type":"FILE","user":"SY"},{"id":"244","name":"서울시외","type":"FILE","user":"Santiago"},{"id":"296","name":"오륜동","type":"FILE","user":"JY"},{"id":"299","name":"잠실3동","type":"FILE","user":"JH"},{"id":"305","name":"거여1동","type":"FILE","user":"Royd"},{"id":"312","name":"둔촌1동","type":"FILE","user":"Gasfard"},{"id":"316","name":"가락2동","type":"FILE","user":"Santiago"},{"id":"344","name":"문정1동","type":"FILE","user":"Santiago"},{"id":"351","name":"방이2동","type":"FILE","user":"Pel"},{"id":"372","name":"성내3동","type":"FILE","user":"Gasfard"},{"id":"423","name":"가락본동","type":"FILE","user":"YS"},{"id":"495","name":"거여2동","type":"FILE","user":"JY"},{"id":"540","name":"천호3동","type":"FILE","user":"MS"}],"edges":[{"sourceNodeId":"6","targetNodeId":"219","score":0.050896138},{"sourceNodeId":"72","targetNodeId":"219","score":0.01608456},{"sourceNodeId":"73","targetNodeId":"219","score":0.012178309},{"sourceNodeId":"126","targetNodeId":"219","score":0.01573989},{"sourceNodeId":"142","targetNodeId":"219","score":0.012063419},{"sourceNodeId":"143","targetNodeId":"219","score":0.01160386},{"sourceNodeId":"160","targetNodeId":"219","score":0.14349724},{"sourceNodeId":"190","targetNodeId":"219","score":0.032054227},{"sourceNodeId":"202","targetNodeId":"219","score":0.018841911},{"sourceNodeId":"219","targetNodeId":"237","score":0.08857996},{"sourceNodeId":"219","targetNodeId":"244","score":0.028262869},{"sourceNodeId":"219","targetNodeId":"296","score":0.01585478},{"sourceNodeId":"219","targetNodeId":"299","score":0.022748161},{"sourceNodeId":"219","targetNodeId":"305","score":0.026079964},{"sourceNodeId":"219","targetNodeId":"312","score":0.022403494},{"sourceNodeId":"219","targetNodeId":"316","score":0.057215072},{"sourceNodeId":"219","targetNodeId":"344","score":0.01551011},{"sourceNodeId":"219","targetNodeId":"351","score":0.03446691},{"sourceNodeId":"219","targetNodeId":"372","score":0.03102022},{"sourceNodeId":"219","targetNodeId":"423","score":0.059168197},{"sourceNodeId":"219","targetNodeId":"495","score":0.016429229},{"sourceNodeId":"219","targetNodeId":"540","score":0.01585478}]}