{"meta":{"learningDate":[2023,10,13,15,26],"applyDate":[2023,10,13,15,26],"method":"Relation","algorithm":["CosineSimilarity"]},"nodes":[{"id":"1","name":"명동","type":"FILE","user":"YS"},{"id":"7","name":"종로1.2.3.4가동","type":"FILE","user":"JY"},{"id":"17","name":"종로5.6가동","type":"FILE","user":"Charlie"},{"id":"54","name":"전농1동","type":"FILE","user":"JY"},{"id":"67","name":"이화동","type":"FILE","user":"Royd"},{"id":"88","name":"삼선동","type":"FILE","user":"Royd"},{"id":"90","name":"번1동","type":"FILE","user":"Royd"},{"id":"108","name":"혜화동","type":"FILE","user":"MS"},{"id":"111","name":"수유3동","type":"FILE","user":"SY"},{"id":"124","name":"송중동","type":"FILE","user":"MS"},{"id":"132","name":"송천동","type":"FILE","user":"Pierre"},{"id":"146","name":"미아동","type":"FILE","user":"Santiago"},{"id":"153","name":"길음1동","type":"FILE","user":"YS"},{"id":"187","name":"제기동","type":"FILE","user":"MS"},{"id":"192","name":"종암동","type":"FILE","user":"Gasfard"},{"id":"200","name":"수유1동","type":"FILE","user":"JH"},{"id":"205","name":"안암동","type":"FILE","user":"SY"},{"id":"213","name":"정릉2동","type":"FILE","user":"JH"},{"id":"223","name":"인수동","type":"FILE","user":"Pel"},{"id":"225","name":"월곡1동","type":"FILE","user":"Charlie"},{"id":"232","name":"정릉4동","type":"FILE","user":"Pierre"},{"id":"243","name":"도봉1동","type":"FILE","user":"JY"},{"id":"244","name":"서울시외","type":"FILE","user":"Santiago"},{"id":"245","name":"동선동","type":"FILE","user":"Gasfard"},{"id":"253","name":"삼각산동","type":"FILE","user":"Santiago"},{"id":"254","name":"수유2동","type":"FILE","user":"Pel"},{"id":"284","name":"길음2동","type":"FILE","user":"JY"},{"id":"311","name":"삼양동","type":"FILE","user":"JH"},{"id":"334","name":"정릉1동","type":"FILE","user":"Santiago"},{"id":"349","name":"정릉3동","type":"FILE","user":"JY"},{"id":"354","name":"장위1동","type":"FILE","user":"Pierre"},{"id":"402","name":"쌍문3동","type":"FILE","user":"Dhino"},{"id":"405","name":"돈암1동","type":"FILE","user":"SY"}],"edges":[{"sourceNodeId":"1","targetNodeId":"284","score":0.01160386},{"sourceNodeId":"7","targetNodeId":"284","score":0.06410845},{"sourceNodeId":"17","targetNodeId":"284","score":0.012408088},{"sourceNodeId":"54","targetNodeId":"284","score":0.01171875},{"sourceNodeId":"67","targetNodeId":"284","score":0.018152574},{"sourceNodeId":"88","targetNodeId":"284","score":0.029756434},{"sourceNodeId":"90","targetNodeId":"284","score":0.014590993},{"sourceNodeId":"108","targetNodeId":"284","score":0.012752757},{"sourceNodeId":"111","targetNodeId":"284","score":0.029641544},{"sourceNodeId":"124","targetNodeId":"284","score":0.026309744},{"sourceNodeId":"132","targetNodeId":"284","score":0.07766544},{"sourceNodeId":"146","targetNodeId":"284","score":0.01619945},{"sourceNodeId":"153","targetNodeId":"284","score":0.140625},{"sourceNodeId":"187","targetNodeId":"284","score":0.037798714},{"sourceNodeId":"192","targetNodeId":"284","score":0.08972886},{"sourceNodeId":"200","targetNodeId":"284","score":0.04710478},{"sourceNodeId":"205","targetNodeId":"284","score":0.012982537},{"sourceNodeId":"213","targetNodeId":"284","score":0.01953125},{"sourceNodeId":"223","targetNodeId":"284","score":0.013556985},{"sourceNodeId":"225","targetNodeId":"284","score":0.03929228},{"sourceNodeId":"232","targetNodeId":"284","score":0.041475184},{"sourceNodeId":"243","targetNodeId":"284","score":0.013212316},{"sourceNodeId":"244","targetNodeId":"284","score":0.033777572},{"sourceNodeId":"245","targetNodeId":"284","score":0.057789523},{"sourceNodeId":"253","targetNodeId":"284","score":0.052389707},{"sourceNodeId":"254","targetNodeId":"284","score":0.014246323},{"sourceNodeId":"284","targetNodeId":"311","score":0.033547793},{"sourceNodeId":"284","targetNodeId":"334","score":0.040670957},{"sourceNodeId":"284","targetNodeId":"349","score":0.030445771},{"sourceNodeId":"284","targetNodeId":"354","score":0.013671875},{"sourceNodeId":"284","targetNodeId":"402","score":0.014131434},{"sourceNodeId":"284","targetNodeId":"405","score":0.042394303}]}