{"meta":{"learningDate":[2023,10,13,15,26],"applyDate":[2023,10,13,15,26],"method":"Relation","algorithm":["CosineSimilarity"]},"nodes":[{"id":"1","name":"명동","type":"FILE","user":"YS"},{"id":"3","name":"회현동","type":"FILE","user":"JH"},{"id":"4","name":"서교동","type":"FILE","user":"Pel"},{"id":"5","name":"화곡1동","type":"FILE","user":"Dhino"},{"id":"8","name":"신촌동","type":"FILE","user":"YS"},{"id":"12","name":"한강로동","type":"FILE","user":"Gasfard"},{"id":"14","name":"여의동","type":"FILE","user":"JY"},{"id":"16","name":"역삼1동","type":"FILE","user":"Dhino"},{"id":"18","name":"대흥동","type":"FILE","user":"Royd"},{"id":"19","name":"사직동","type":"FILE","user":"Gasfard"},{"id":"27","name":"목1동","type":"FILE","user":"MS"},{"id":"28","name":"성산2동","type":"FILE","user":"Gasfard"},{"id":"36","name":"상암동","type":"FILE","user":"JY"},{"id":"41","name":"서강동","type":"FILE","user":"Santiago"},{"id":"53","name":"공덕동","type":"FILE","user":"MS"},{"id":"70","name":"갈현1동","type":"FILE","user":"Royd"},{"id":"113","name":"압구정동","type":"FILE","user":"Pierre"},{"id":"123","name":"충현동","type":"FILE","user":"Dhino"},{"id":"133","name":"신사1동","type":"FILE","user":"JH"},{"id":"173","name":"신당동","type":"FILE","user":"Charlie"},{"id":"174","name":"청파동","type":"FILE","user":"Gasfard"},{"id":"209","name":"월곡2동","type":"FILE","user":"Pel"},{"id":"242","name":"신사2동","type":"FILE","user":"Dhino"},{"id":"244","name":"서울시외","type":"FILE","user":"Santiago"},{"id":"298","name":"약수동","type":"FILE","user":"Gasfard"},{"id":"307","name":"한남동","type":"FILE","user":"Gasfard"},{"id":"348","name":"용산2가동","type":"FILE","user":"Dhino"},{"id":"366","name":"원효로1동","type":"FILE","user":"Gasfard"},{"id":"378","name":"이태원1동","type":"FILE","user":"SY"},{"id":"388","name":"효창동","type":"FILE","user":"SY"},{"id":"531","name":"용문동","type":"FILE","user":"MS"}],"edges":[{"sourceNodeId":"1","targetNodeId":"388","score":0.012982537},{"sourceNodeId":"3","targetNodeId":"388","score":0.052849263},{"sourceNodeId":"4","targetNodeId":"388","score":0.110523894},{"sourceNodeId":"5","targetNodeId":"388","score":0.025390625},{"sourceNodeId":"8","targetNodeId":"388","score":0.012867647},{"sourceNodeId":"12","targetNodeId":"388","score":0.09466912},{"sourceNodeId":"14","targetNodeId":"388","score":0.037339155},{"sourceNodeId":"16","targetNodeId":"388","score":0.016429229},{"sourceNodeId":"18","targetNodeId":"388","score":0.07019761},{"sourceNodeId":"19","targetNodeId":"388","score":0.029641544},{"sourceNodeId":"27","targetNodeId":"388","score":0.01171875},{"sourceNodeId":"28","targetNodeId":"388","score":0.034352023},{"sourceNodeId":"36","targetNodeId":"388","score":0.036420036},{"sourceNodeId":"41","targetNodeId":"388","score":0.060431987},{"sourceNodeId":"53","targetNodeId":"388","score":0.12293199},{"sourceNodeId":"70","targetNodeId":"388","score":0.014246323},{"sourceNodeId":"113","targetNodeId":"388","score":0.025735294},{"sourceNodeId":"123","targetNodeId":"388","score":0.03079044},{"sourceNodeId":"133","targetNodeId":"388","score":0.04365809},{"sourceNodeId":"173","targetNodeId":"388","score":0.024471506},{"sourceNodeId":"174","targetNodeId":"388","score":0.06158088},{"sourceNodeId":"209","targetNodeId":"388","score":0.01171875},{"sourceNodeId":"242","targetNodeId":"388","score":0.012522978},{"sourceNodeId":"244","targetNodeId":"388","score":0.017807905},{"sourceNodeId":"298","targetNodeId":"388","score":0.029641544},{"sourceNodeId":"307","targetNodeId":"388","score":0.047909006},{"sourceNodeId":"348","targetNodeId":"388","score":0.038028494},{"sourceNodeId":"366","targetNodeId":"388","score":0.01573989},{"sourceNodeId":"378","targetNodeId":"388","score":0.041934744},{"sourceNodeId":"388","targetNodeId":"531","score":0.012867647}]}