{"meta":{"learningDate":[2023,10,13,15,26],"applyDate":[2023,10,13,15,26],"method":"Relation","algorithm":["CosineSimilarity"]},"nodes":[{"id":"52","name":"망우본동","type":"FILE","user":"JY"},{"id":"54","name":"전농1동","type":"FILE","user":"JY"},{"id":"78","name":"성수2가3동","type":"FILE","user":"JH"},{"id":"85","name":"화양동","type":"FILE","user":"Pel"},{"id":"136","name":"면목본동","type":"FILE","user":"Pel"},{"id":"151","name":"상봉2동","type":"FILE","user":"Charlie"},{"id":"167","name":"장안2동","type":"FILE","user":"Royd"},{"id":"207","name":"면목3.8동","type":"FILE","user":"MS"},{"id":"244","name":"서울시외","type":"FILE","user":"Santiago"},{"id":"340","name":"휘경2동","type":"FILE","user":"JY"},{"id":"390","name":"면목7동","type":"FILE","user":"Dhino"},{"id":"393","name":"면목2동","type":"FILE","user":"Santiago"},{"id":"503","name":"면목5동","type":"FILE","user":"Pierre"}],"edges":[{"sourceNodeId":"52","targetNodeId":"503","score":0.015280331},{"sourceNodeId":"54","targetNodeId":"503","score":0.016429229},{"sourceNodeId":"78","targetNodeId":"503","score":0.012752757},{"sourceNodeId":"85","targetNodeId":"503","score":0.017003676},{"sourceNodeId":"136","targetNodeId":"503","score":0.030330881},{"sourceNodeId":"151","targetNodeId":"503","score":0.026079964},{"sourceNodeId":"167","targetNodeId":"503","score":0.032743566},{"sourceNodeId":"207","targetNodeId":"503","score":0.045266543},{"sourceNodeId":"244","targetNodeId":"503","score":0.012293198},{"sourceNodeId":"340","targetNodeId":"503","score":0.012522978},{"sourceNodeId":"390","targetNodeId":"503","score":0.01918658},{"sourceNodeId":"393","targetNodeId":"503","score":0.014361213}]}