{"meta":{"learningDate":[2023,10,13,15,26],"applyDate":[2023,10,13,15,26],"method":"Relation","algorithm":["CosineSimilarity"]},"nodes":[{"id":"141","name":"신흥2동","type":"FILE","user":"SY"},{"id":"244","name":"서울시외","type":"FILE","user":"Santiago"},{"id":"294","name":"태평1동","type":"FILE","user":"Gasfard"},{"id":"442","name":"태평2동","type":"FILE","user":"Pierre"},{"id":"462","name":"신흥3동","type":"FILE","user":"YS"},{"id":"469","name":"상대원1동","type":"FILE","user":"Dhino"},{"id":"557","name":"태평3동","type":"FILE","user":"Dhino"}],"edges":[{"sourceNodeId":"141","targetNodeId":"557","score":0.012408088},{"sourceNodeId":"244","targetNodeId":"557","score":0.015625},{"sourceNodeId":"294","targetNodeId":"557","score":0.0201057},{"sourceNodeId":"442","targetNodeId":"557","score":0.013442095},{"sourceNodeId":"462","targetNodeId":"557","score":0.016544119},{"sourceNodeId":"469","targetNodeId":"557","score":0.012178309}]}