{"meta":{"learningDate":[2023,10,13,15,26],"applyDate":[2023,10,13,15,26],"method":"Relation","algorithm":["CosineSimilarity"]},"nodes":[{"id":"1","name":"명동","type":"FILE","user":"YS"},{"id":"2","name":"서초2동","type":"FILE","user":"Charlie"},{"id":"3","name":"회현동","type":"FILE","user":"JH"},{"id":"4","name":"서교동","type":"FILE","user":"Pel"},{"id":"6","name":"잠실6동","type":"FILE","user":"SY"},{"id":"7","name":"종로1.2.3.4가동","type":"FILE","user":"JY"},{"id":"9","name":"청룡동","type":"FILE","user":"MS"},{"id":"10","name":"대치4동","type":"FILE","user":"MS"},{"id":"11","name":"대치2동","type":"FILE","user":"Dhino"},{"id":"14","name":"여의동","type":"FILE","user":"JY"},{"id":"15","name":"서초3동","type":"FILE","user":"Santiago"},{"id":"16","name":"역삼1동","type":"FILE","user":"Dhino"},{"id":"19","name":"사직동","type":"FILE","user":"Gasfard"},{"id":"20","name":"남현동","type":"FILE","user":"JY"},{"id":"21","name":"서원동","type":"FILE","user":"Dhino"},{"id":"24","name":"삼성2동","type":"FILE","user":"JY"},{"id":"25","name":"당산2동","type":"FILE","user":"Charlie"},{"id":"26","name":"용신동","type":"FILE","user":"SY"},{"id":"29","name":"수서동","type":"FILE","user":"Santiago"},{"id":"30","name":"반포4동","type":"FILE","user":"JY"},{"id":"33","name":"서초1동","type":"FILE","user":"JH"},{"id":"35","name":"세곡동","type":"FILE","user":"Charlie"},{"id":"39","name":"을지로동","type":"FILE","user":"Dhino"},{"id":"43","name":"삼성1동","type":"FILE","user":"Charlie"},{"id":"45","name":"양재1동","type":"FILE","user":"JH"},{"id":"46","name":"상일동","type":"FILE","user":"JH"},{"id":"51","name":"덕풍3동","type":"FILE","user":"Santiago"},{"id":"56","name":"구의3동","type":"FILE","user":"SY"},{"id":"58","name":"잠실2동","type":"FILE","user":"YS"},{"id":"63","name":"양재2동","type":"FILE","user":"JY"},{"id":"64","name":"인헌동","type":"FILE","user":"YS"},{"id":"66","name":"구로3동","type":"FILE","user":"JH"},{"id":"72","name":"성내2동","type":"FILE","user":"JH"},{"id":"73","name":"문정2동","type":"FILE","user":"Gasfard"},{"id":"78","name":"성수2가3동","type":"FILE","user":"JH"},{"id":"79","name":"능동","type":"FILE","user":"Charlie"},{"id":"83","name":"가락1동","type":"FILE","user":"Pel"},{"id":"84","name":"강일동","type":"FILE","user":"Pel"},{"id":"85","name":"화양동","type":"FILE","user":"Pel"},{"id":"87","name":"논현1동","type":"FILE","user":"YS"},{"id":"89","name":"논현2동","type":"FILE","user":"Pel"},{"id":"100","name":"암사2동","type":"FILE","user":"MS"},{"id":"113","name":"압구정동","type":"FILE","user":"Pierre"},{"id":"117","name":"일원본동","type":"FILE","user":"JY"},{"id":"121","name":"수진1동","type":"FILE","user":"Royd"},{"id":"126","name":"장지동","type":"FILE","user":"Santiago"},{"id":"131","name":"잠실4동","type":"FILE","user":"JY"},{"id":"139","name":"용답동","type":"FILE","user":"SY"},{"id":"141","name":"신흥2동","type":"FILE","user":"SY"},{"id":"142","name":"석촌동","type":"FILE","user":"JY"},{"id":"143","name":"위례동","type":"FILE","user":"Royd"},{"id":"145","name":"구의1동","type":"FILE","user":"Pel"},{"id":"148","name":"광장동","type":"FILE","user":"SY"},{"id":"149","name":"도곡1동","type":"FILE","user":"Pierre"},{"id":"151","name":"상봉2동","type":"FILE","user":"Charlie"},{"id":"160","name":"오금동","type":"FILE","user":"Pierre"},{"id":"164","name":"천호1동","type":"FILE","user":"Santiago"},{"id":"166","name":"잠실본동","type":"FILE","user":"Pel"},{"id":"172","name":"명일1동","type":"FILE","user":"Charlie"},{"id":"177","name":"명일2동","type":"FILE","user":"Pierre"},{"id":"178","name":"행당1동","type":"FILE","user":"Dhino"},{"id":"181","name":"단대동","type":"FILE","user":"Pel"},{"id":"190","name":"송파1동","type":"FILE","user":"Pel"},{"id":"193","name":"도곡2동","type":"FILE","user":"Pierre"},{"id":"202","name":"길동","type":"FILE","user":"JH"},{"id":"219","name":"마천2동","type":"FILE","user":"Pierre"},{"id":"230","name":"삼전동","type":"FILE","user":"Gasfard"},{"id":"236","name":"개포2동","type":"FILE","user":"Dhino"},{"id":"237","name":"마천1동","type":"FILE","user":"SY"},{"id":"244","name":"서울시외","type":"FILE","user":"Santiago"},{"id":"261","name":"구의2동","type":"FILE","user":"YS"},{"id":"263","name":"성내1동","type":"FILE","user":"Charlie"},{"id":"277","name":"자양2동","type":"FILE","user":"Pel"},{"id":"282","name":"둔촌2동","type":"FILE","user":"MS"},{"id":"294","name":"태평1동","type":"FILE","user":"Gasfard"},{"id":"295","name":"백현동","type":"FILE","user":"Pierre"},{"id":"299","name":"잠실3동","type":"FILE","user":"JH"},{"id":"305","name":"거여1동","type":"FILE","user":"Royd"},{"id":"312","name":"둔촌1동","type":"FILE","user":"Gasfard"},{"id":"316","name":"가락2동","type":"FILE","user":"Santiago"},{"id":"322","name":"야탑1동","type":"FILE","user":"Pierre"},{"id":"343","name":"자양1동","type":"FILE","user":"Pel"},{"id":"344","name":"문정1동","type":"FILE","user":"Santiago"},{"id":"351","name":"방이2동","type":"FILE","user":"Pel"},{"id":"359","name":"구미동","type":"FILE","user":"SY"},{"id":"410","name":"성복동","type":"FILE","user":"SY"},{"id":"418","name":"산성동","type":"FILE","user":"Pierre"},{"id":"423","name":"가락본동","type":"FILE","user":"YS"},{"id":"424","name":"서현1동","type":"FILE","user":"Santiago"},{"id":"451","name":"성남동","type":"FILE","user":"Royd"},{"id":"462","name":"신흥3동","type":"FILE","user":"YS"},{"id":"498","name":"수진2동","type":"FILE","user":"YS"},{"id":"501","name":"죽전2동","type":"FILE","user":"Gasfard"},{"id":"528","name":"수내1동","type":"FILE","user":"Gasfard"},{"id":"577","name":"구갈동","type":"FILE","user":"Dhino"},{"id":"595","name":"이매1동","type":"FILE","user":"Charlie"}],"edges":[{"sourceNodeId":"1","targetNodeId":"73","score":0.03561581},{"sourceNodeId":"2","targetNodeId":"73","score":0.087431066},{"sourceNodeId":"3","targetNodeId":"73","score":0.012408088},{"sourceNodeId":"4","targetNodeId":"73","score":0.030101104},{"sourceNodeId":"6","targetNodeId":"73","score":0.32398897},{"sourceNodeId":"7","targetNodeId":"73","score":0.026309744},{"sourceNodeId":"9","targetNodeId":"73","score":0.05767463},{"sourceNodeId":"10","targetNodeId":"73","score":0.12373621},{"sourceNodeId":"11","targetNodeId":"73","score":0.09777114},{"sourceNodeId":"14","targetNodeId":"73","score":0.049977023},{"sourceNodeId":"15","targetNodeId":"73","score":0.0625},{"sourceNodeId":"16","targetNodeId":"73","score":0.14028034},{"sourceNodeId":"19","targetNodeId":"73","score":0.012637868},{"sourceNodeId":"20","targetNodeId":"73","score":0.04710478},{"sourceNodeId":"21","targetNodeId":"73","score":0.03584559},{"sourceNodeId":"24","targetNodeId":"73","score":0.057789523},{"sourceNodeId":"25","targetNodeId":"73","score":0.012293198},{"sourceNodeId":"26","targetNodeId":"73","score":0.01171875},{"sourceNodeId":"29","targetNodeId":"73","score":0.1573989},{"sourceNodeId":"30","targetNodeId":"73","score":0.037224263},{"sourceNodeId":"33","targetNodeId":"73","score":0.06353401},{"sourceNodeId":"35","targetNodeId":"73","score":0.14797795},{"sourceNodeId":"39","targetNodeId":"73","score":0.03216912},{"sourceNodeId":"43","targetNodeId":"73","score":0.049057905},{"sourceNodeId":"45","targetNodeId":"73","score":0.07157629},{"sourceNodeId":"46","targetNodeId":"73","score":0.03814338},{"sourceNodeId":"51","targetNodeId":"73","score":0.09501379},{"sourceNodeId":"56","targetNodeId":"73","score":0.041130513},{"sourceNodeId":"58","targetNodeId":"73","score":0.037683822},{"sourceNodeId":"63","targetNodeId":"73","score":0.017463235},{"sourceNodeId":"64","targetNodeId":"73","score":0.025735294},{"sourceNodeId":"66","targetNodeId":"73","score":0.03067555},{"sourceNodeId":"72","targetNodeId":"73","score":0.22598805},{"sourceNodeId":"73","targetNodeId":"78","score":0.039407168},{"sourceNodeId":"73","targetNodeId":"79","score":0.052964155},{"sourceNodeId":"73","targetNodeId":"83","score":0.21909466},{"sourceNodeId":"73","targetNodeId":"84","score":0.01171875},{"sourceNodeId":"73","targetNodeId":"85","score":0.056870405},{"sourceNodeId":"73","targetNodeId":"87","score":0.04342831},{"sourceNodeId":"73","targetNodeId":"89","score":0.059168197},{"sourceNodeId":"73","targetNodeId":"100","score":0.15016085},{"sourceNodeId":"73","targetNodeId":"113","score":0.052734375},{"sourceNodeId":"73","targetNodeId":"117","score":0.074908085},{"sourceNodeId":"73","targetNodeId":"121","score":0.11224724},{"sourceNodeId":"73","targetNodeId":"126","score":0.15314798},{"sourceNodeId":"73","targetNodeId":"131","score":0.0803079},{"sourceNodeId":"73","targetNodeId":"139","score":0.05055147},{"sourceNodeId":"73","targetNodeId":"141","score":0.20151654},{"sourceNodeId":"73","targetNodeId":"142","score":0.20519301},{"sourceNodeId":"73","targetNodeId":"143","score":0.14866728},{"sourceNodeId":"73","targetNodeId":"145","score":0.044577207},{"sourceNodeId":"73","targetNodeId":"148","score":0.042164523},{"sourceNodeId":"73","targetNodeId":"149","score":0.026654411},{"sourceNodeId":"73","targetNodeId":"151","score":0.012178309},{"sourceNodeId":"73","targetNodeId":"160","score":0.046989888},{"sourceNodeId":"73","targetNodeId":"164","score":0.038028494},{"sourceNodeId":"73","targetNodeId":"166","score":0.052389707},{"sourceNodeId":"73","targetNodeId":"172","score":0.029526655},{"sourceNodeId":"73","targetNodeId":"177","score":0.025390625},{"sourceNodeId":"73","targetNodeId":"178","score":0.030560661},{"sourceNodeId":"73","targetNodeId":"181","score":0.15567555},{"sourceNodeId":"73","targetNodeId":"190","score":0.021943934},{"sourceNodeId":"73","targetNodeId":"193","score":0.058478862},{"sourceNodeId":"73","targetNodeId":"202","score":0.04204963},{"sourceNodeId":"73","targetNodeId":"219","score":0.012178309},{"sourceNodeId":"73","targetNodeId":"230","score":0.036420036},{"sourceNodeId":"73","targetNodeId":"236","score":0.049287684},{"sourceNodeId":"73","targetNodeId":"237","score":0.028033089},{"sourceNodeId":"73","targetNodeId":"244","score":0.2120864},{"sourceNodeId":"73","targetNodeId":"261","score":0.041130513},{"sourceNodeId":"73","targetNodeId":"263","score":0.11029412},{"sourceNodeId":"73","targetNodeId":"277","score":0.012063419},{"sourceNodeId":"73","targetNodeId":"282","score":0.025045956},{"sourceNodeId":"73","targetNodeId":"294","score":0.06870405},{"sourceNodeId":"73","targetNodeId":"295","score":0.029526655},{"sourceNodeId":"73","targetNodeId":"299","score":0.028262869},{"sourceNodeId":"73","targetNodeId":"305","score":0.014705882},{"sourceNodeId":"73","targetNodeId":"312","score":0.024701286},{"sourceNodeId":"73","targetNodeId":"316","score":0.048138786},{"sourceNodeId":"73","targetNodeId":"322","score":0.14085478},{"sourceNodeId":"73","targetNodeId":"343","score":0.013212316},{"sourceNodeId":"73","targetNodeId":"344","score":0.017922794},{"sourceNodeId":"73","targetNodeId":"351","score":0.029641544},{"sourceNodeId":"73","targetNodeId":"359","score":0.11822151},{"sourceNodeId":"73","targetNodeId":"410","score":0.013901655},{"sourceNodeId":"73","targetNodeId":"418","score":0.06410845},{"sourceNodeId":"73","targetNodeId":"423","score":0.022633271},{"sourceNodeId":"73","targetNodeId":"424","score":0.10052849},{"sourceNodeId":"73","targetNodeId":"451","score":0.091337316},{"sourceNodeId":"73","targetNodeId":"462","score":0.061121322},{"sourceNodeId":"73","targetNodeId":"498","score":0.07134651},{"sourceNodeId":"73","targetNodeId":"501","score":0.0625},{"sourceNodeId":"73","targetNodeId":"528","score":0.051585477},{"sourceNodeId":"73","targetNodeId":"577","score":0.032628678},{"sourceNodeId":"73","targetNodeId":"595","score":0.012867647}]}